[
  {"timestamp": "2024-05-01T12:00:00", "interpretive_bandwidth": 0.65, "symbolic_density": 0.70, "divergence_space": 0.50},
  {"timestamp": "2024-05-05T12:00:00", "interpretive_bandwidth": 0.66, "symbolic_density": 0.72, "divergence_space": 0.51},
  {"timestamp": "2024-05-10T12:00:00", "interpretive_bandwidth": 0.68, "symbolic_density": 0.73, "divergence_space": 0.52},
  {"timestamp": "2024-05-15T12:00:00", "interpretive_bandwidth": 0.67, "symbolic_density": 0.71, "divergence_space": 0.51},
  {"timestamp": "2024-05-20T12:00:00", "interpretive_bandwidth": 0.69, "symbolic_density": 0.74, "divergence_space": 0.53},
  {"timestamp": "2024-05-25T12:00:00", "interpretive_bandwidth": 0.70, "symbolic_density": 0.75, "divergence_space": 0.55},
  {"timestamp": "2024-05-30T12:00:00", "interpretive_bandwidth": 0.71, "symbolic_density": 0.76, "divergence_space": 0.56},
  {"timestamp": "2024-06-04T12:00:00", "interpretive_bandwidth": 0.72, "symbolic_density": 0.77, "divergence_space": 0.57},
  {"timestamp": "2024-06-09T12:00:00", "interpretive_bandwidth": 0.73, "symbolic_density": 0.78, "divergence_space": 0.58},
  {"timestamp": "2024-06-14T12:00:00", "interpretive_bandwidth": 0.74, "symbolic_density": 0.79, "divergence_space": 0.59}
]
